backend/__init__.py
backend/remote.py
backend/server.py
backend/site.py
backend/sql_backup.py
backend/tsite.py
backend/wikibackup.py
frontend/__init__.py
frontend/clickstream.py
frontend/cmsmain.py
frontend/frame.py
frontend/html_table.py
frontend/servers_view.py
frontend/version.py
frontend/webscrape.py
frontend/webserver.py
frontend/wikicms.py
frontend/wikigrid.py
frontend/wikis_view.py
frontend/resources/__init__.py
frontend/resources/schema.yaml
pywikicms-0.4.6.dist-info/METADATA
pywikicms-0.4.6.dist-info/WHEEL
pywikicms-0.4.6.dist-info/entry_points.txt
pywikicms-0.4.6.dist-info/licenses/LICENSE
pywikicms-0.4.6.dist-info/RECORD
