Metadata-Version: 2.4
Name: pyWikiCMS
Version: 0.4.6
Summary: pyWikiCMS: python implementation of a Mediawiki based Content Management System
Project-URL: Home, https://github.com/BITPlan/pyWikiCMS
Project-URL: Documentation, https://wiki.bitplan.com/index.php/PyWikiCMS
Project-URL: Source, https://github.com/BITPlan/pyWikiCMS
Author-email: Wolfgang Fahl <wf@bitplan.com>
Maintainer-email: Wolfgang Fahl <wf@bitplan.com>
License: Apache-2.0
License-File: LICENSE
Classifier: Development Status :: 4 - Beta
Classifier: Environment :: Web Environment
Classifier: Intended Audience :: Developers
Classifier: Intended Audience :: Education
Classifier: Intended Audience :: Science/Research
Classifier: License :: OSI Approved :: Apache Software License
Classifier: Operating System :: OS Independent
Classifier: Programming Language :: Python :: 3 :: Only
Classifier: Programming Language :: Python :: 3.10
Classifier: Programming Language :: Python :: 3.11
Classifier: Programming Language :: Python :: 3.12
Classifier: Programming Language :: Python :: 3.13
Classifier: Topic :: Software Development :: User Interfaces
Requires-Python: >=3.10
Requires-Dist: beautifulsoup4>=4.9.3
Requires-Dist: lxml
Requires-Dist: ngwidgets>=0.29.4
Requires-Dist: nicegraph>=0.0.2
Requires-Dist: py-3rdparty-mediawiki>=0.17.0
Requires-Dist: pybasemkit>=0.1.1
Requires-Dist: pydevd
Requires-Dist: pylodstorage>=0.17.5
Requires-Dist: pymogwai>=0.1.0
Requires-Dist: pymysql>=1.1.1
Requires-Dist: rdflib>=7.0.0
Provides-Extra: test
Requires-Dist: green; extra == 'test'
